fast_tools/__init__.py
fast_tools/base/__init__.py
fast_tools/base/_json.py
fast_tools/base/lru.py
fast_tools/base/middleware.py
fast_tools/base/redis_helper.py
fast_tools/base/route_trie.py
fast_tools/base/utils.py
fast_tools/cache.py
fast_tools/cbv.py
fast_tools/config.py
fast_tools/context.py
fast_tools/customer_json.py
fast_tools/exporter/__init__.py
fast_tools/exporter/handle.py
fast_tools/exporter/middleware.py
fast_tools/exporter/util.py
fast_tools/lazy_property.py
fast_tools/limit/__init__.py
fast_tools/limit/backend/__init__.py
fast_tools/limit/backend/base.py
fast_tools/limit/backend/memory.py
fast_tools/limit/backend/redis.py
fast_tools/limit/decorator.py
fast_tools/limit/func.py
fast_tools/limit/middleware.py
fast_tools/limit/rule.py
fast_tools/limit/util.py
fast_tools/share.py
fast_tools/statsd_middleware.py
fast_tools/task.py
fast_tools-1.1.2.dist-info/LICENSE
fast_tools-1.1.2.dist-info/WHEEL
fast_tools-1.1.2.dist-info/METADATA
fast_tools-1.1.2.dist-info/RECORD
