Metadata-Version: 2.1
Name: fast-tools
Version: 1.1.2
Summary: fast-tools is a FastApi/Starlette toolset, Most of the tools can be used in FastApi/Starlette, a few tools only support FastApi which is divided into the lack of compatibility with FastApi
Home-page: https://github.com/so1n/fast-tools
License: MIT
Author: So1n
Author-email: so1n897046026@gmail.com
Requires-Python: >=3.7,<4.0
Classifier: License :: OSI Approved :: MIT License
Classifier: Programming Language :: Python :: 3
Classifier: Programming Language :: Python :: 3.7
Classifier: Programming Language :: Python :: 3.8
Classifier: Programming Language :: Python :: 3.9
Provides-Extra: config
Provides-Extra: ojson
Provides-Extra: prometheus
Provides-Extra: pydantic
Provides-Extra: redis
Provides-Extra: statsd
Provides-Extra: ujson
Requires-Dist: PyYAML (>=5.4.1,<6.0.0)
Requires-Dist: aio-statsd (==0.2.6); extra == "statsd"
Requires-Dist: aioredis (>=1.3.1,<2.0.0); extra == "redis"
Requires-Dist: environs (>=9.3.1,<10.0.0); extra == "config"
Requires-Dist: ojson (>=0.1.0,<0.2.0); extra == "ojson"
Requires-Dist: prometheus-client (>=0.9.0,<0.10.0); extra == "prometheus"
Requires-Dist: pydantic (>=1.8.1,<2.0.0); extra == "pydantic"
Requires-Dist: ujson (>=4.0.2,<5.0.0); extra == "ujson"
Project-URL: Repository, https://github.com/so1n/fast-tools
